pydialogue/__init__.py
pydialogue/dialogue_generator.py
pydialogue/baseline/__init__.py
pydialogue/baseline/evaluation.py
pydialogue/baseline/llm_base_policies.py
pydialogue/baseline/llm_policies.py
pydialogue/baseline/rag_policies.py
pydialogue/baseline/serializers.py
pydialogue/environment/__init__.py
pydialogue/environment/actions.py
pydialogue/environment/descriptions.py
pydialogue/environment/entities.py
pydialogue/environment/helpers.py
pydialogue/environments/__init__.py
pydialogue/environments/builders.py
pydialogue/environments/easy.py
pydialogue/environments/path_helpers.py
pydialogue/environments/world.py
pydialogue/generation/__init__.py
pydialogue/generation/dialogue.py
pydialogue/generation/file_list_db.py
pydialogue/generation/goal_generators.py
pydialogue/generation/helpers.py
pydialogue/generation/mappers_database.py
pydialogue/generation/param_generators.py
pydialogue/generation/templates.py
pydialogue/language/__init__.py
pydialogue/language/components.py
pydialogue/language/desc_mappers.py
pydialogue/language/describers.py
pydialogue/language/helpers.py
pydialogue/language/phrases.py
pydialogue/language/queries.py
pydialogue/language/sentences.py
pydialogue/language/words.py
pydialogue/policies/__init__.py
pydialogue/policies/agent_policies.py
pydialogue/policies/base_policies.py
pydialogue/policies/env_policies.py
pydialogue/policies/goals.py
pydialogue/policies/other_policies.py
pydialogue/policies/policies_helpers.py
pydialogue/policies/user_policies.py
pydialogue/policies/vocab.py
pydialogue/state/__init__.py
pydialogue/state/kn_checkers.py
pydialogue/state/kn_helpers.py
pydialogue/state/kn_parsers.py
pydialogue/state/kn_updaters.py
pydialogue/state/knowledge_base.py
pydialogue-0.1.0.dist-info/METADATA
pydialogue-0.1.0.dist-info/WHEEL
pydialogue-0.1.0.dist-info/licenses/LICENSE.md
pydialogue-0.1.0.dist-info/RECORD
