Metadata-Version: 2.4
Name: pydialogue
Version: 0.1.0
Summary: A library for simulating dialogues.
Project-URL: Homepage, https://github.com/smartinovski/pydialogue
Project-URL: Issues, https://github.com/smartinovski/pydialogue/issues
Project-URL: Contribute, https://github.com/smartinovski/pydialogue#contribute
Project-URL: Support Us, https://github.com/smartinovski/pydialogue#support-us
Author-email: Stefan Martinovski <pydialogue@outlook.com>
License-File: LICENSE.md
Classifier: License :: OSI Approved :: MIT License
Classifier: Operating System :: OS Independent
Classifier: Programming Language :: Python :: 3
Requires-Python: >=3.10
Requires-Dist: dijkstar
Requires-Dist: file-read-backwards
Requires-Dist: ipywidgets
Requires-Dist: matplotlib
Requires-Dist: nltk
Requires-Dist: notebook
Requires-Dist: pyinflect
Requires-Dist: tqdm
